katbeam/__init__.py
katbeam/jimbeam.py
katbeam-0.1.dist-info/LICENSE.txt
katbeam-0.1.dist-info/METADATA
katbeam-0.1.dist-info/WHEEL
katbeam-0.1.dist-info/top_level.txt
katbeam-0.1.dist-info/RECORD
